Patoman/Ghost.py
Patoman/Matriz.py
Patoman/__init__.py
Patoman/main.py
Patoman/matriz.txt
Patoman/menu.py
Patoman/fonts/emulogic.ttf
Patoman/imgs/BlinkyDown1.png
Patoman/imgs/BlinkyDown2.png
Patoman/imgs/BlinkyLeft1.png
Patoman/imgs/BlinkyLeft2.png
Patoman/imgs/BlinkyRight1.png
Patoman/imgs/BlinkyRight2.png
Patoman/imgs/BlinkyUp1.png
Patoman/imgs/BlinkyUp2.png
Patoman/imgs/ClydeDown1.png
Patoman/imgs/ClydeDown2.png
Patoman/imgs/ClydeLeft1.png
Patoman/imgs/ClydeLeft2.png
Patoman/imgs/ClydeRight1.png
Patoman/imgs/ClydeRight2.png
Patoman/imgs/ClydeUp1.png
Patoman/imgs/ClydeUp2.png
Patoman/imgs/EatenDown.png
Patoman/imgs/EatenLeft.png
Patoman/imgs/EatenRight.png
Patoman/imgs/EatenUp.png
Patoman/imgs/Frightened1.png
Patoman/imgs/Frightened2.png
Patoman/imgs/FrightenedBlink1.png
Patoman/imgs/FrightenedBlink2.png
Patoman/imgs/InkyDown1.png
Patoman/imgs/InkyDown2.png
Patoman/imgs/InkyLeft1.png
Patoman/imgs/InkyLeft2.png
Patoman/imgs/InkyRight1.png
Patoman/imgs/InkyRight2.png
Patoman/imgs/InkyUp1.png
Patoman/imgs/InkyUp2.png
Patoman/imgs/PinkyDown1.png
Patoman/imgs/PinkyDown2.png
Patoman/imgs/PinkyLeft1.png
Patoman/imgs/PinkyLeft2.png
Patoman/imgs/PinkyRight1.png
Patoman/imgs/PinkyRight2.png
Patoman/imgs/PinkyUp1.png
Patoman/imgs/PinkyUp2.png
Patoman/imgs/arrow.png
Patoman/imgs/background.png
Patoman/imgs/background_open.png
Patoman/imgs/background_white.png
Patoman/imgs/bit.png
Patoman/imgs/corn.png
Patoman/imgs/patoAB.png
Patoman/imgs/patoAC.png
Patoman/imgs/patoAD.png
Patoman/imgs/patoAE.png
Patoman/imgs/patoFB.png
Patoman/imgs/patoFC.png
Patoman/imgs/patoFD.png
Patoman/imgs/patoFE.png
Patoman/imgs/patoman_logo.png
Patoman/imgs/score0.png
Patoman/imgs/score1.png
Patoman/imgs/score2.png
Patoman/imgs/score3.png
Patoman/sounds/1up.wav
Patoman/sounds/begin.wav
Patoman/sounds/death.wav
Patoman/sounds/eat.wav
Patoman/sounds/eyes.wav
Patoman/sounds/menu_music.wav
Patoman/sounds/music1.wav
Patoman/sounds/music2.wav
Patoman/sounds/music3.wav
Patoman/sounds/music4.wav
Pato_man-1.0.dist-info/LICENSE
Pato_man-1.0.dist-info/METADATA
Pato_man-1.0.dist-info/WHEEL
Pato_man-1.0.dist-info/entry_points.txt
Pato_man-1.0.dist-info/top_level.txt
Pato_man-1.0.dist-info/RECORD
