Metadata-Version: 2.1
Name: Pato-man
Version: 1.0
Summary: Pac-man with ducks
Home-page: https://github.com/AbraaoCF/Pato-man
Author: Abraão Caiana de Freitas
Author-email: abraao.freitas@ccc.ufcg.edu.br
License: UNKNOWN
Platform: UNKNOWN
Classifier: Programming Language :: Python :: 3
Classifier: License :: OSI Approved :: MIT License
Classifier: Operating System :: OS Independent
Requires-Python: >=3.6
Requires-Dist: pygame
